skyhook/__init__.py
skyhook/main.py
skyhook/security.py
skyhook/server.py
skyhook/templates/index.html
skyhook_rayan-1.1.1.dist-info/licenses/LICENSE
skyhook_rayan-1.1.1.dist-info/METADATA
skyhook_rayan-1.1.1.dist-info/WHEEL
skyhook_rayan-1.1.1.dist-info/entry_points.txt
skyhook_rayan-1.1.1.dist-info/top_level.txt
skyhook_rayan-1.1.1.dist-info/RECORD
