Metadata-Version: 2.4
Name: skyhook-rayan
Version: 1.1.1
Summary: A secure, zero-config CLI file server with upload capabilities and encrypted transport
Author: Skyhook Contributors
License: MIT
Project-URL: Homepage, https://github.com/skyhook/skyhook
Project-URL: Documentation, https://github.com/skyhook/skyhook#readme
Project-URL: Repository, https://github.com/skyhook/skyhook
Keywords: file-server,upload,cli,fastapi,security
Classifier: Development Status :: 4 - Beta
Classifier: Intended Audience :: Developers
Classifier: License :: OSI Approved :: MIT License
Classifier: Programming Language :: Python :: 3
Classifier: Programming Language :: Python :: 3.9
Classifier: Programming Language :: Python :: 3.10
Classifier: Programming Language :: Python :: 3.11
Classifier: Programming Language :: Python :: 3.12
Requires-Python: >=3.9
License-File: LICENSE
Requires-Dist: fastapi>=0.109.0
Requires-Dist: uvicorn[standard]>=0.27.0
Requires-Dist: python-multipart>=0.0.6
Requires-Dist: jinja2>=3.1.2
Requires-Dist: typer>=0.9.0
Requires-Dist: cryptography>=41.0.0
Provides-Extra: dev
Requires-Dist: pytest>=7.4.0; extra == "dev"
Requires-Dist: pytest-asyncio>=0.21.0; extra == "dev"
Requires-Dist: httpx>=0.26.0; extra == "dev"
Dynamic: license-file
